{"An Innocent Nun.png":{"total_gen_time":165532,"user_word_count":161,"non_user_word_count":1508,"user_msg_count":5,"non_user_msg_count":9,"total_swipe_count":0,"chat_size":22261,"date_last_chat":1688618237322,"date_first_chat":1688566893006},"Anaconda.png":{"total_gen_time":14086146,"user_word_count":51083,"non_user_word_count":160547,"user_msg_count":1512,"non_user_msg_count":1874,"total_swipe_count":127,"chat_size":2320316,"date_last_chat":1718112996565,"date_first_chat":1688257281653},"Aqua.png":{"total_gen_time":410867,"user_word_count":2210,"non_user_word_count":2080,"user_msg_count":153,"non_user_msg_count":215,"total_swipe_count":55,"chat_size":24134,"date_last_chat":1718594254546,"date_first_chat":1688123896545},"Darkness.png":{"total_gen_time":0,"user_word_count":0,"non_user_word_count":126,"user_msg_count":0,"non_user_msg_count":2,"total_swipe_count":0,"chat_size":1173,"date_last_chat":1689552163828,"date_first_chat":253402300799999},"Gina_1.png":{"total_gen_time":8984864,"user_word_count":46301,"non_user_word_count":101036,"user_msg_count":1708,"non_user_msg_count":2071,"total_swipe_count":160,"chat_size":1253360,"date_last_chat":1718481815521,"date_first_chat":1689594226190},"Guard.png":{"total_gen_time":0,"user_word_count":0,"non_user_word_count":6,"user_msg_count":0,"non_user_msg_count":1,"total_swipe_count":0,"chat_size":363,"date_last_chat":1689552143265,"date_first_chat":253402300799999},"Karla.png":{"total_gen_time":7766955,"user_word_count":17676,"non_user_word_count":96113,"user_msg_count":543,"non_user_msg_count":694,"total_swipe_count":11,"chat_size":1495828,"date_last_chat":1717567304106,"date_first_chat":1688132872410},"Lucy1.png":{"total_gen_time":12023636,"user_word_count":29352,"non_user_word_count":241789,"user_msg_count":1132,"non_user_msg_count":1535,"total_swipe_count":20,"chat_size":3625584,"date_last_chat":1704925220343,"date_first_chat":1688723436369},"Marota.png":{"total_gen_time":20496,"user_word_count":70,"non_user_word_count":619,"user_msg_count":3,"non_user_msg_count":4,"total_swipe_count":0,"chat_size":8850,"date_last_chat":1689381669165,"date_first_chat":1689424754155},"Megumin.png":{"total_gen_time":0,"user_word_count":0,"non_user_word_count":65,"user_msg_count":0,"non_user_msg_count":1,"total_swipe_count":0,"chat_size":506,"date_last_chat":1688077803360,"date_first_chat":253402300799999},"Olivia1.png":{"total_gen_time":1644390,"user_word_count":3357,"non_user_word_count":36127,"user_msg_count":157,"non_user_msg_count":212,"total_swipe_count":0,"chat_size":523173,"date_last_chat":1699440459889,"date_first_chat":1688998668419},"Oppai Imp.png":{"total_gen_time":1261228,"user_word_count":1436,"non_user_word_count":8077,"user_msg_count":49,"non_user_msg_count":55,"total_swipe_count":0,"chat_size":118905,"date_last_chat":1689132886964,"date_first_chat":1688126978020},"Robin (male).png":{"total_gen_time":67830,"user_word_count":93,"non_user_word_count":1434,"user_msg_count":8,"non_user_msg_count":11,"total_swipe_count":0,"chat_size":22003,"date_last_chat":1689644886536,"date_first_chat":1688476931207},"Rouge the Bat1.png":{"total_gen_time":0,"user_word_count":0,"non_user_word_count":0,"user_msg_count":0,"non_user_msg_count":0,"total_swipe_count":0,"chat_size":0,"date_last_chat":0,"date_first_chat":253402300799999},"Selena.png":{"total_gen_time":372954,"user_word_count":951,"non_user_word_count":4124,"user_msg_count":22,"non_user_msg_count":23,"total_swipe_count":0,"chat_size":61656,"date_last_chat":1688362345640,"date_first_chat":1688200871370},"Sexadroid.png":{"total_gen_time":1610610,"user_word_count":2330,"non_user_word_count":16765,"user_msg_count":134,"non_user_msg_count":163,"total_swipe_count":3,"chat_size":249097,"date_last_chat":1718590401964,"date_first_chat":1688460872551},"Sexy Rouge the Bat.png":{"total_gen_time":15974,"user_word_count":6,"non_user_word_count":236,"user_msg_count":1,"non_user_msg_count":2,"total_swipe_count":0,"chat_size":3018,"date_last_chat":1688362349249,"date_first_chat":1688399796734},"Suki.png":{"total_gen_time":916965,"user_word_count":1448,"non_user_word_count":9109,"user_msg_count":55,"non_user_msg_count":78,"total_swipe_count":6,"chat_size":132853,"date_last_chat":1702157918952,"date_first_chat":1688373788819},"timestamp":1718594788859,"Catherine_1.png":{"total_gen_time":2490357,"user_msg_count":636,"non_user_msg_count":779,"user_word_count":14874,"non_user_word_count":9385,"total_swipe_count":58,"date_last_chat":1711923611324,"date_first_chat":1693953015142}}